{
	"DeepsightDropTableDefinition": 50,
	"DeepsightMomentDefinition": 2,
	"DeepsightPlugCategorisation": 13,
	"DeepsightWallpaperDefinition": 2,
	"Enums": 12,
	"Destiny2/Manifest": "223071.24.01.20.1700-2-bnet.53755",
	"Interfaces": 11,
	"deepsight": 111,
	"DeepsightTierTypeDefinition": 1,
	"lastDailyReset": "2024-02-03T17:00:00Z",
	"lastWeeklyReset": "2024-01-30T17:00:00Z",
	"lastTrialsReset": "2024-02-02T17:00:00Z",
	"referencePostGameCarnageReportSinceDailyReset": {
		"instanceId": "14400589636",
		"period": "2024-02-03T17:24:42Z"
	},
	"updated": "2024-02-04T01:32:19Z",
	"DeepsightVendorDefinition": 27
}
